license
rin_exceptions/__init__.py
rin_exceptions/main.py
rin_exceptions-1.0.3.dist-info/LICENSE
rin_exceptions-1.0.3.dist-info/WHEEL
rin_exceptions-1.0.3.dist-info/METADATA
rin_exceptions-1.0.3.dist-info/RECORD
