Metadata-Version: 2.1
Name: rin-exceptions
Version: 1.0.3
Summary: A set of base exceptions for Rin
Home-page: https://github.com/No767/Rin-Exceptions
License: Apache-2.0
Author: No767
Author-email: 73260931+No767@users.noreply.github.com
Requires-Python: >=3.7,<4.0
Classifier: Development Status :: 5 - Production/Stable
Classifier: Intended Audience :: Developers
Classifier: License :: OSI Approved :: Apache Software License
Classifier: Operating System :: OS Independent
Classifier: Programming Language :: Python :: 3
Classifier: Programming Language :: Python :: 3.10
Classifier: Programming Language :: Python :: 3.7
Classifier: Programming Language :: Python :: 3.8
Classifier: Programming Language :: Python :: 3.9
Classifier: Programming Language :: Python :: Implementation :: CPython
Project-URL: Repository, https://github.com/No767/Rin-Exceptions
